Metadata-Version: 2.1
Name: cdiscount-api-client
Version: 0.0.8
Summary: A simple api client for cdiscount marketplace
Home-page: https://github.com/sathouel/cdiscount_api_client
Author: Steven Athouel
Author-email: sathouel@gmail.com
License: UNKNOWN
Platform: UNKNOWN
Classifier: Programming Language :: Python :: 3
Classifier: License :: OSI Approved :: MIT License
Classifier: Operating System :: OS Independent
Requires-Python: >=3.6
